<annotation>
	<folder>my-project-name</folder>
	<filename>144446982_jpg.rf.83152064412e26181d5d270b93152e59.jpg</filename>
	<path>/my-project-name/144446982_jpg.rf.83152064412e26181d5d270b93152e59.jpg</path>
	<source>
		<database>roboflow.ai</database>
	</source>
	<size>
		<width>640</width>
		<height>640</height>
		<depth>3</depth>
	</size>
	<segmented>0</segmented>
	<object>
		<name>8S</name>
		<pose>Unspecified</pose>
		<truncated>0</truncated>
		<difficult>0</difficult>
		<occluded>0</occluded>
		<bndbox>
			<xmin>265</xmin>
			<xmax>307</xmax>
			<ymin>279</ymin>
			<ymax>304</ymax>
		</bndbox>
	</object>
	<object>
		<name>8S</name>
		<pose>Unspecified</pose>
		<truncated>0</truncated>
		<difficult>0</difficult>
		<occluded>0</occluded>
		<bndbox>
			<xmin>262</xmin>
			<xmax>305</xmax>
			<ymin>238</ymin>
			<ymax>256</ymax>
		</bndbox>
	</object>
	<object>
		<name>AC</name>
		<pose>Unspecified</pose>
		<truncated>0</truncated>
		<difficult>0</difficult>
		<occluded>0</occluded>
		<bndbox>
			<xmin>267</xmin>
			<xmax>309</xmax>
			<ymin>206</ymin>
			<ymax>227</ymax>
		</bndbox>
	</object>
	<object>
		<name>AC</name>
		<pose>Unspecified</pose>
		<truncated>0</truncated>
		<difficult>0</difficult>
		<occluded>0</occluded>
		<bndbox>
			<xmin>422</xmin>
			<xmax>466</xmax>
			<ymin>120</ymin>
			<ymax>141</ymax>
		</bndbox>
	</object>
</annotation>
