<annotation>
	<folder>my-project-name</folder>
	<filename>194983305_jpg.rf.883273f560d655afec1d44c3774de8f1.jpg</filename>
	<path>/my-project-name/194983305_jpg.rf.883273f560d655afec1d44c3774de8f1.jpg</path>
	<source>
		<database>roboflow.ai</database>
	</source>
	<size>
		<width>640</width>
		<height>640</height>
		<depth>3</depth>
	</size>
	<segmented>0</segmented>
	<object>
		<name>4H</name>
		<pose>Unspecified</pose>
		<truncated>0</truncated>
		<difficult>0</difficult>
		<occluded>0</occluded>
		<bndbox>
			<xmin>314</xmin>
			<xmax>347</xmax>
			<ymin>266</ymin>
			<ymax>327</ymax>
		</bndbox>
	</object>
	<object>
		<name>JC</name>
		<pose>Unspecified</pose>
		<truncated>0</truncated>
		<difficult>0</difficult>
		<occluded>0</occluded>
		<bndbox>
			<xmin>266</xmin>
			<xmax>292</xmax>
			<ymin>268</ymin>
			<ymax>331</ymax>
		</bndbox>
	</object>
	<object>
		<name>8D</name>
		<pose>Unspecified</pose>
		<truncated>0</truncated>
		<difficult>0</difficult>
		<occluded>0</occluded>
		<bndbox>
			<xmin>189</xmin>
			<xmax>219</xmax>
			<ymin>257</ymin>
			<ymax>321</ymax>
		</bndbox>
	</object>
	<object>
		<name>8D</name>
		<pose>Unspecified</pose>
		<truncated>0</truncated>
		<difficult>0</difficult>
		<occluded>0</occluded>
		<bndbox>
			<xmin>62</xmin>
			<xmax>92</xmax>
			<ymin>14</ymin>
			<ymax>78</ymax>
		</bndbox>
	</object>
</annotation>
