<annotation>
	<folder>my-project-name</folder>
	<filename>332405548_jpg.rf.e12cc03a21ef12d5e5dbfe761e735879.jpg</filename>
	<path>/my-project-name/332405548_jpg.rf.e12cc03a21ef12d5e5dbfe761e735879.jpg</path>
	<source>
		<database>roboflow.ai</database>
	</source>
	<size>
		<width>640</width>
		<height>640</height>
		<depth>3</depth>
	</size>
	<segmented>0</segmented>
	<object>
		<name>10H</name>
		<pose>Unspecified</pose>
		<truncated>0</truncated>
		<difficult>0</difficult>
		<occluded>0</occluded>
		<bndbox>
			<xmin>405</xmin>
			<xmax>469</xmax>
			<ymin>247</ymin>
			<ymax>280</ymax>
		</bndbox>
	</object>
	<object>
		<name>2D</name>
		<pose>Unspecified</pose>
		<truncated>0</truncated>
		<difficult>0</difficult>
		<occluded>0</occluded>
		<bndbox>
			<xmin>383</xmin>
			<xmax>444</xmax>
			<ymin>305</ymin>
			<ymax>345</ymax>
		</bndbox>
	</object>
	<object>
		<name>5H</name>
		<pose>Unspecified</pose>
		<truncated>0</truncated>
		<difficult>0</difficult>
		<occluded>0</occluded>
		<bndbox>
			<xmin>351</xmin>
			<xmax>410</xmax>
			<ymin>354</ymin>
			<ymax>398</ymax>
		</bndbox>
	</object>
	<object>
		<name>5H</name>
		<pose>Unspecified</pose>
		<truncated>0</truncated>
		<difficult>0</difficult>
		<occluded>0</occluded>
		<bndbox>
			<xmin>75</xmin>
			<xmax>134</xmax>
			<ymin>371</ymin>
			<ymax>414</ymax>
		</bndbox>
	</object>
</annotation>
