<annotation>
	<folder>my-project-name</folder>
	<filename>419169741_jpg.rf.1c607ce43fb9d7d86defb7e301d78ff0.jpg</filename>
	<path>/my-project-name/419169741_jpg.rf.1c607ce43fb9d7d86defb7e301d78ff0.jpg</path>
	<source>
		<database>roboflow.ai</database>
	</source>
	<size>
		<width>640</width>
		<height>640</height>
		<depth>3</depth>
	</size>
	<segmented>0</segmented>
	<object>
		<name>7H</name>
		<pose>Unspecified</pose>
		<truncated>0</truncated>
		<difficult>0</difficult>
		<occluded>0</occluded>
		<bndbox>
			<xmin>324</xmin>
			<xmax>350</xmax>
			<ymin>323</ymin>
			<ymax>366</ymax>
		</bndbox>
	</object>
	<object>
		<name>KH</name>
		<pose>Unspecified</pose>
		<truncated>0</truncated>
		<difficult>0</difficult>
		<occluded>0</occluded>
		<bndbox>
			<xmin>289</xmin>
			<xmax>318</xmax>
			<ymin>310</ymin>
			<ymax>352</ymax>
		</bndbox>
	</object>
	<object>
		<name>4C</name>
		<pose>Unspecified</pose>
		<truncated>0</truncated>
		<difficult>0</difficult>
		<occluded>0</occluded>
		<bndbox>
			<xmin>245</xmin>
			<xmax>281</xmax>
			<ymin>279</ymin>
			<ymax>314</ymax>
		</bndbox>
	</object>
	<object>
		<name>4C</name>
		<pose>Unspecified</pose>
		<truncated>0</truncated>
		<difficult>0</difficult>
		<occluded>0</occluded>
		<bndbox>
			<xmin>257</xmin>
			<xmax>293</xmax>
			<ymin>104</ymin>
			<ymax>139</ymax>
		</bndbox>
	</object>
</annotation>
