<annotation>
	<folder>my-project-name</folder>
	<filename>489483317_jpg.rf.56e637670927e7cbf63ecf4c13ca2915.jpg</filename>
	<path>/my-project-name/489483317_jpg.rf.56e637670927e7cbf63ecf4c13ca2915.jpg</path>
	<source>
		<database>roboflow.ai</database>
	</source>
	<size>
		<width>640</width>
		<height>640</height>
		<depth>3</depth>
	</size>
	<segmented>0</segmented>
	<object>
		<name>3S</name>
		<pose>Unspecified</pose>
		<truncated>0</truncated>
		<difficult>0</difficult>
		<occluded>0</occluded>
		<bndbox>
			<xmin>480</xmin>
			<xmax>522</xmax>
			<ymin>320</ymin>
			<ymax>350</ymax>
		</bndbox>
	</object>
	<object>
		<name>4S</name>
		<pose>Unspecified</pose>
		<truncated>0</truncated>
		<difficult>0</difficult>
		<occluded>0</occluded>
		<bndbox>
			<xmin>464</xmin>
			<xmax>501</xmax>
			<ymin>345</ymin>
			<ymax>377</ymax>
		</bndbox>
	</object>
	<object>
		<name>KC</name>
		<pose>Unspecified</pose>
		<truncated>0</truncated>
		<difficult>0</difficult>
		<occluded>0</occluded>
		<bndbox>
			<xmin>416</xmin>
			<xmax>461</xmax>
			<ymin>381</ymin>
			<ymax>420</ymax>
		</bndbox>
	</object>
	<object>
		<name>KC</name>
		<pose>Unspecified</pose>
		<truncated>0</truncated>
		<difficult>0</difficult>
		<occluded>0</occluded>
		<bndbox>
			<xmin>250</xmin>
			<xmax>294</xmax>
			<ymin>343</ymin>
			<ymax>382</ymax>
		</bndbox>
	</object>
</annotation>
