<annotation>
	<folder>my-project-name</folder>
	<filename>597242383_jpg.rf.6417da11bbb7160b936beab422ff00ed.jpg</filename>
	<path>/my-project-name/597242383_jpg.rf.6417da11bbb7160b936beab422ff00ed.jpg</path>
	<source>
		<database>roboflow.ai</database>
	</source>
	<size>
		<width>640</width>
		<height>640</height>
		<depth>3</depth>
	</size>
	<segmented>0</segmented>
	<object>
		<name>9H</name>
		<pose>Unspecified</pose>
		<truncated>0</truncated>
		<difficult>0</difficult>
		<occluded>0</occluded>
		<bndbox>
			<xmin>246</xmin>
			<xmax>276</xmax>
			<ymin>181</ymin>
			<ymax>244</ymax>
		</bndbox>
	</object>
	<object>
		<name>10C</name>
		<pose>Unspecified</pose>
		<truncated>0</truncated>
		<difficult>0</difficult>
		<occluded>0</occluded>
		<bndbox>
			<xmin>307</xmin>
			<xmax>339</xmax>
			<ymin>185</ymin>
			<ymax>249</ymax>
		</bndbox>
	</object>
	<object>
		<name>7D</name>
		<pose>Unspecified</pose>
		<truncated>0</truncated>
		<difficult>0</difficult>
		<occluded>0</occluded>
		<bndbox>
			<xmin>361</xmin>
			<xmax>399</xmax>
			<ymin>205</ymin>
			<ymax>268</ymax>
		</bndbox>
	</object>
	<object>
		<name>7D</name>
		<pose>Unspecified</pose>
		<truncated>0</truncated>
		<difficult>0</difficult>
		<occluded>0</occluded>
		<bndbox>
			<xmin>455</xmin>
			<xmax>493</xmax>
			<ymin>466</ymin>
			<ymax>529</ymax>
		</bndbox>
	</object>
</annotation>
