<annotation>
	<folder>my-project-name</folder>
	<filename>787875607_jpg.rf.5979067e6ce7e15d153e1dc365c39f17.jpg</filename>
	<path>/my-project-name/787875607_jpg.rf.5979067e6ce7e15d153e1dc365c39f17.jpg</path>
	<source>
		<database>roboflow.ai</database>
	</source>
	<size>
		<width>640</width>
		<height>640</height>
		<depth>3</depth>
	</size>
	<segmented>0</segmented>
	<object>
		<name>QC</name>
		<pose>Unspecified</pose>
		<truncated>0</truncated>
		<difficult>0</difficult>
		<occluded>0</occluded>
		<bndbox>
			<xmin>224</xmin>
			<xmax>279</xmax>
			<ymin>545</ymin>
			<ymax>597</ymax>
		</bndbox>
	</object>
	<object>
		<name>5C</name>
		<pose>Unspecified</pose>
		<truncated>0</truncated>
		<difficult>0</difficult>
		<occluded>0</occluded>
		<bndbox>
			<xmin>185</xmin>
			<xmax>246</xmax>
			<ymin>491</ymin>
			<ymax>534</ymax>
		</bndbox>
	</object>
	<object>
		<name>JH</name>
		<pose>Unspecified</pose>
		<truncated>0</truncated>
		<difficult>0</difficult>
		<occluded>0</occluded>
		<bndbox>
			<xmin>172</xmin>
			<xmax>234</xmax>
			<ymin>434</ymin>
			<ymax>463</ymax>
		</bndbox>
	</object>
	<object>
		<name>JH</name>
		<pose>Unspecified</pose>
		<truncated>0</truncated>
		<difficult>0</difficult>
		<occluded>0</occluded>
		<bndbox>
			<xmin>344</xmin>
			<xmax>406</xmax>
			<ymin>225</ymin>
			<ymax>254</ymax>
		</bndbox>
	</object>
</annotation>
